{
    "ParsingVersion": "1.0",
    "CORPUS": [
        {
            "version": "1.0",
            "ARCHI_VERSIONS_COMPATIBILITIES": [
                "VERSION_1",
                "VERSION_2",
                "VERSION_3"
            ],
            "DECLARATIVE_TYPES": [
                {
                    "CONCEPTUAL_NAME": "BusinessType",
                    "IS_ABSTRACT": "TRUE",
                    "Attributes": [
                        {
                            "CONCEPTUAL_NAME": "id",
                            "DB_MAPPING": [
                                {
                                    "DB": "_Index",
                                    "Mapping": "physicalid"
                                },
                                {
                                    "DB": "_3DSpaceDB",
                                    "Mapping": "physicalid"
                                }
                            ]
                        },
                        {
                            "CONCEPTUAL_NAME": "interface",
                            "DB_MAPPING": [
                                {
                                    "DB": "_Index",
                                    "Mapping": "interface"
                                },
                                {
                                    "DB": "_3DSpaceDB",
                                    "Mapping": "interface"
                                }
                            ]
                        },
                        {
                            "CONCEPTUAL_NAME": "type",
                            "DB_MAPPING": [
                                {
                                    "DB": "_Index",
                                    "Mapping": "type"
                                },
                                {
                                    "DB": "_3DSpaceDB",
                                    "Mapping": "type"
                                }
                            ]
                        },
                        {
                            "CONCEPTUAL_NAME": "logicalid",
                            "DB_MAPPING": [
                                {
                                    "DB": "_Index",
                                    "Mapping": "logicalid"
                                },
                                {
                                    "DB": "_3DSpaceDB",
                                    "Mapping": "logicalid"
                                }
                            ]
                        },
                        {
                            "CONCEPTUAL_NAME": "cestamp",
                            "DB_MAPPING": [
                                {
                                    "DB": "_3DSpaceDB",
                                    "Mapping": "cestamp"
                                },
                                {
                                    "DB": "_Index",
                                    "Mapping": "cestamp"
                                }
                            ]
                        },
                        {
                            "CONCEPTUAL_NAME": "state",
                            "DB_MAPPING": [
                                {
                                    "DB": "_3DSpaceDB",
                                    "Mapping": "current"
                                },
                                {
                                    "DB": "_Index",
                                    "Mapping": "current"
                                }
                            ]
                        },
                        {
                            "CONCEPTUAL_NAME": "modified",
                            "DB_MAPPING": [
                                {
                                    "DB": "_3DSpaceDB",
                                    "Mapping": "modified"
                                },
                                {
                                    "DB": "_Index",
                                    "Mapping": "modified"
                                }
                            ]
                        },
                        {
                            "CONCEPTUAL_NAME": "organization",
                            "DB_MAPPING": [
                                {
                                    "DB": "_3DSpaceDB",
                                    "Mapping": "organization"
                                },
                                {
                                    "DB": "_Index",
                                    "Mapping": "organization"
                                }
                            ]
                        },
                        {
                            "CONCEPTUAL_NAME": "created",
                            "DB_MAPPING": [
                                {
                                    "DB": "_3DSpaceDB",
                                    "Mapping": "originated"
                                },
                                {
                                    "DB": "_Index",
                                    "Mapping": "originated"
                                }
                            ]
                        },
                        {
                            "CONCEPTUAL_NAME": "owner",
                            "DB_MAPPING": [
                                {
                                    "DB": "_3DSpaceDB",
                                    "Mapping": "owner"
                                },
                                {
                                    "DB": "_Index",
                                    "Mapping": "owner"
                                }
                            ]
                        },
                        {
                            "CONCEPTUAL_NAME": "revision",
                            "DB_MAPPING": [
                                {
                                    "DB": "_3DSpaceDB",
                                    "Mapping": "revision"
                                },
                                {
                                    "DB": "_Index",
                                    "Mapping": "revision"
                                }
                            ]
                        },
                        {
                            "CONCEPTUAL_NAME": "collabspace",
                            "DB_MAPPING": [
                                {
                                    "DB": "_3DSpaceDB",
                                    "Mapping": "project"
                                },
                                {
                                    "DB": "_Index",
                                    "Mapping": "project"
                                }
                            ]
                        },
                        {
                        	"CONCEPTUAL_NAME": "kind"
                        },
                        {
                        	"CONCEPTUAL_NAME": "groupedKind"
                        }
                    ]
                },
                {
                    "CONCEPTUAL_NAME": "RelationType",
                    "IS_ABSTRACT": "TRUE",
                    "Attributes": [
                        {
                            "CONCEPTUAL_NAME": "id",
                            "DB_MAPPING": [
                                {
                                    "DB": "_Index",
                                    "Mapping": "physicalid"
                                },
                                {
                                    "DB": "_3DSpaceDB",
                                    "Mapping": "physicalid"
                                }
                            ]
                        },
                        {
                            "CONCEPTUAL_NAME": "cestamp",
                            "DB_MAPPING": [
                                {
                                    "DB": "_3DSpaceDB",
                                    "Mapping": "cestamp"
                                },
                                {
                                    "DB": "_Index",
                                    "Mapping": "cestamp"
                                }
                            ]
                        },
                        {
                            "CONCEPTUAL_NAME": "interface",
                            "DB_MAPPING": [
                                {
                                    "DB": "_Index",
                                    "Mapping": "interface"
                                },
                                {
                                    "DB": "_3DSpaceDB",
                                    "Mapping": "interface"
                                }
                            ]
                        },
                        {
                            "CONCEPTUAL_NAME": "type",
                            "DB_MAPPING": [
                                {
                                    "DB": "_Index",
                                    "Mapping": "type"
                                },
                                {
                                    "DB": "_3DSpaceDB",
                                    "Mapping": "type"
                                }
                            ]
                        },
                        {
                            "CONCEPTUAL_NAME": "logicalid",
                            "DB_MAPPING": [
                                {
                                    "DB": "_Index",
                                    "Mapping": "logicalid"
                                },
                                {
                                    "DB": "_3DSpaceDB",
                                    "Mapping": "logicalid"
                                }
                            ]
                        },
                        {
                            "CONCEPTUAL_NAME": "organization",
                            "DB_MAPPING": [
                                {
                                    "DB": "_3DSpaceDB",
                                    "Mapping": "organization"
                                },
                                {
                                    "DB": "_Index",
                                    "Mapping": "organization"
                                }
                            ]
                        },
                        {
                            "CONCEPTUAL_NAME": "originated",
                            "DB_MAPPING": [
                                {
                                    "DB": "_3DSpaceDB",
                                    "Mapping": "originated"
                                },
                                {
                                    "DB": "_Index",
                                    "Mapping": "originated"
                                }
                            ]
                        },
                        {
                            "CONCEPTUAL_NAME": "created",
                            "DB_MAPPING": [
                                {
                                    "DB": "_3DSpaceDB",
                                    "Mapping": "originated"
                                },
                                {
                                    "DB": "_Index",
                                    "Mapping": "originated"
                                }
                            ]
                        },                        
                        {
                            "CONCEPTUAL_NAME": "owner",
                            "DB_MAPPING": [
                                {
                                    "DB": "_3DSpaceDB",
                                    "Mapping": "owner"
                                },
                                {
                                    "DB": "_Index",
                                    "Mapping": "owner"
                                }
                            ]
                        },
                        {
                            "CONCEPTUAL_NAME": "collabspace",
                            "DB_MAPPING": [
                                {
                                    "DB": "_3DSpaceDB",
                                    "Mapping": "project"
                                },
                                {
                                    "DB": "_Index",
                                    "Mapping": "project"
                                }
                            ]
                        },
                        {
                        	"CONCEPTUAL_NAME": "kind"
                        },
                        {
                        	"CONCEPTUAL_NAME": "grouped_kind"
                        }
                    ]
                },
                {
                    "CONCEPTUAL_NAME": "PLMEntity",
                    "PARENT_TYPE": "BusinessType",
                    "IS_ABSTRACT": "TRUE",
                    "Attributes": [
                        {
                            "CONCEPTUAL_NAME": "name",
                            "DB_MAPPING": [
                                {
                                    "DB": "_3DSpaceDB",
                                    "Mapping": "PLMEntity.PLM_ExternalID"
                                },
                                {
                                    "DB": "_Index",
                                    "Mapping": "bo.PLMEntity.PLM_ExternalID"
                                }
                            ]
                        },
                        {
                            "CONCEPTUAL_NAME": "title",
                            "DB_MAPPING": [
                                {
                                    "DB": "_3DSpaceDB",
                                    "Mapping": "PLMEntity.V_Name"
                                },
                                {
                                    "DB": "_Index",
                                    "Mapping": "bo.PLMEntity.V_Name"
                                }
                            ]
                        },
                        {
                            "CONCEPTUAL_NAME": "description",
                            "DB_MAPPING": [
                                {
                                    "DB": "_3DSpaceDB",
                                    "Mapping": "PLMEntity.V_description"
                                },
                                {
                                    "DB": "_Index",
                                    "Mapping": "bo.PLMEntity.V_description"
                                }
                            ]
                        }
                    ]
                },
                {
                    "CONCEPTUAL_NAME": "PLMReference",
                    "PARENT_TYPE": "PLMEntity",
                    "IS_ABSTRACT": "TRUE",
                    "Attributes": [
                        {
                            "CONCEPTUAL_NAME": "versionComment",
                            "DB_MAPPING": [
                                {
                                    "DB": "_3DSpaceDB",
                                    "Mapping": "PLMReference.V_versionComment"
                                },
                                {
                                    "DB": "_Index",
                                    "Mapping": "bo.PLMReference.V_versionComment"
                                }
                            ]
                        }
                    ]
                },
                {
                    "CONCEPTUAL_NAME": "PLMConnection",
                    "PARENT_TYPE": "PLMEntity",
                    "IS_ABSTRACT": "TRUE",
                    "Attributes": [
                        {
                            "CONCEPTUAL_NAME": "composer"
                        }
                    ]
                },
                {
                    "CONCEPTUAL_NAME": "PLMInstance",
                    "PARENT_TYPE": "RelationType",
                    "IS_ABSTRACT": "TRUE",
                    "Attributes": [
                        {
                            "CONCEPTUAL_NAME": "from",
                            "DB_MAPPING": [
                                {
                                    "DB": "_Index",
                                    "Mapping": "from.physicalid"
                                }
                            ],
                            "Checkers": [
                                {
                                    "DB": "_Index",
                                    "Class": "com.dassault_systemes.delmia.crud.services.attributes.checkers.AttributeDefaultChecker"
                                }
                            ]
                        },
                        {
                            "CONCEPTUAL_NAME": "to",
                            "DB_MAPPING": [
                                {
                                    "DB": "_Index",
                                    "Mapping": "to.physicalid"
                                }
                            ],
                            "Checkers": [
                                {
                                    "DB": "_Index",
                                    "Class": "com.dassault_systemes.delmia.crud.services.attributes.checkers.AttributeDefaultChecker"
                                }
                            ]
                        },
                        {
                            "CONCEPTUAL_NAME": "name",
                            "DB_MAPPING": [
                                {
                                    "DB": "_3DSpaceDB",
                                    "Mapping": "PLMInstance.PLM_ExternalID"
                                },
                                {
                                    "DB": "_Index",
                                    "Mapping": "ro.PLMInstance.PLM_ExternalID"
                                }
                            ]
                        },
                        {
                            "CONCEPTUAL_NAME": "title",
                            "DB_MAPPING": [
                                {
                                    "DB": "_3DSpaceDB",
                                    "Mapping": "PLMInstance.V_Name"
                                },
                                {
                                    "DB": "_Index",
                                    "Mapping": "ro.PLMInstance.V_Name"
                                }
                            ]
                        },
                        {
                            "CONCEPTUAL_NAME": "description",
                            "DB_MAPPING": [
                                {
                                    "DB": "_3DSpaceDB",
                                    "Mapping": "PLMInstance.V_description"
                                },
                                {
                                    "DB": "_Index",
                                    "Mapping": "ro.PLMInstance.V_description"
                                }
                            ]
                        }
                    ]
                },            
                {
                    "CONCEPTUAL_NAME": "dsmfg:MfgItem",
                    "PARENT_TYPE": "PLMReference",
                    "IS_ABSTRACT": "TRUE",
                    "DB_MAPPING": [
                        {
                            "DB": "_3DSpaceDB",
                            "Mapping": "DELFmiFunctionReference",
                            "Behavior": "CUSTOM",
                            "Class": "com.dassault_systemes.delmia.crud.mbomservices.behavior.DELMIACRUDPPRMfgItemReferenceExecutionImpl"
                        },
                        {
                            "DB": "_Index",
                            "Mapping": "DELFmiFunctionReference",
                            "Behavior": "REFERENCE"
                        }
                    ],
                    "Attributes": [
                        {
                            "CONCEPTUAL_NAME": "name",
                            "DB_MAPPING": [
                                {
                                    "DB": "_3DSpaceDB",
                                    "Mapping": "PLM_ExternalID"
                                }
                            ]
                        },
                        {
                            "CONCEPTUAL_NAME": "title",
                            "DB_MAPPING": [
                                {
                                    "DB": "_3DSpaceDB",
                                    "Mapping": "V_Name"
                                }
                            ]
                        },
                        {
                            "CONCEPTUAL_NAME": "description",
                            "DB_MAPPING": [
                                {
                                    "DB": "_3DSpaceDB",
                                    "Mapping": "V_description"
                                }
                            ]
                        },
                        {
                            "CONCEPTUAL_NAME": "cestamp",
                            "DB_MAPPING": [
                                {
                                    "DB": "_3DSpaceDB",
                                    "Mapping": "cestamp"
                                }
                            ]
                        },
                        {
                            "CONCEPTUAL_NAME": "state",
                            "DB_MAPPING": [
                                {
                                    "DB": "_3DSpaceDB",
                                    "Mapping": "current"
                                }
                            ]
                        },
                        {
                            "CONCEPTUAL_NAME": "modified",
                            "DB_MAPPING": [
                                {
                                    "DB": "_3DSpaceDB",
                                    "Mapping": "modified"
                                }
                            ]
                        },
                        {
                            "CONCEPTUAL_NAME": "organization",
                            "DB_MAPPING": [
                                {
                                    "DB": "_3DSpaceDB",
                                    "Mapping": "organization"
                                }
                            ]
                        },
                        {
                            "CONCEPTUAL_NAME": "originated",
                            "DB_MAPPING": [
                                {
                                    "DB": "_3DSpaceDB",
                                    "Mapping": "originated"
                                }
                            ]
                        },
                        {
                            "CONCEPTUAL_NAME": "owner",
                            "DB_MAPPING": [
                                {
                                    "DB": "_3DSpaceDB",
                                    "Mapping": "owner"
                                }
                            ]
                        },
                        {
                            "CONCEPTUAL_NAME": "collabspace",
                            "DB_MAPPING": [
                                {
                                    "DB": "_3DSpaceDB",
                                    "Mapping": "project"
                                }
                            ]
                        },
                        {
                            "CONCEPTUAL_NAME": "revision",
                            "DB_MAPPING": [
                                {
                                    "DB": "_3DSpaceDB",
                                    "Mapping": "revision"
                                }
                            ]
                        },
                        {
                            "CONCEPTUAL_NAME": "type",
                            "DB_MAPPING": [
                                {
                                    "DB": "_3DSpaceDB",
                                    "Mapping": "type"
                                }
                            ]
                        },
                        {
                            "CONCEPTUAL_NAME": "isLotNumberRequired",
                            "DB_MAPPING": [
                                {
                                    "DB": "_3DSpaceDB",
                                    "Mapping": "DELAsmLotRefRequired.V_LotNumberRequired"
                                }
                            ]
                        },
                        {
                            "CONCEPTUAL_NAME": "isSerialNumberRequired",
                            "DB_MAPPING": [
                                {
                                    "DB": "_3DSpaceDB",
                                    "Mapping": "DELAsmUnitRefRequired.V_SerialNumberRequired"
                                }
                            ]
                        },
                        {
                            "CONCEPTUAL_NAME": "estimatedTime",
                            "DB_MAPPING": [
                                {
                                    "DB": "_3DSpaceDB",
                                    "Mapping": "DELFmiFunctionReference.V_EstimatedTime"
                                }
                            ]
                        }
                    ]
                },
                {
                    "CONCEPTUAL_NAME": "DELFmiFunctionPPRCreateReference",
                    "PARENT_TYPE": "dsmfg:MfgItem",
                    "IS_ABSTRACT": "TRUE",
                    "DB_MAPPING": [
                        {
                            "DB": "_3DSpaceDB",
                            "Mapping": "DELFmiFunctionPPRCreateReference",
                            "Behavior": "REFERENCE"
                        },
                        {
                            "DB": "_Index",
                            "Mapping": "DELFmiFunctionPPRCreateReference",
                            "Behavior": "REFERENCE"
                        }
                    ],
                    "Attributes": [
	                    {
						    "CONCEPTUAL_NAME": "estimatedCost",
						    "DB_MAPPING": [
						      	{
						        	"DB": "_3DSpaceDB",
						        	"Mapping": "DELFmiFunctionPPRCreateReference.V_EstimatedCost"
						      	}
						    ]
						},
						{
						    "CONCEPTUAL_NAME": "estimatedCostCurrency",
						    "DB_MAPPING": [
						      	{
						        	"DB": "_3DSpaceDB",
						        	"Mapping": "DELFmiFunctionPPRCreateReference.V_EstimatedCostCurrency"
						      	}
						    ]
					    },
					    {
						    "CONCEPTUAL_NAME": "estimatedLeadTimeDescription",
						    "DB_MAPPING": [
						      	{
						        	"DB": "_3DSpaceDB",
						        	"Mapping": "DELFmiFunctionPPRCreateReference.V_EstimatedLeadTimeDescription"
						      	}
						    ]
						},
						{
						    "CONCEPTUAL_NAME": "estimatedWeight",
						    "DB_MAPPING": [
							    {
							        "DB": "_3DSpaceDB",
							        "Mapping": "DELFmiFunctionPPRCreateReference.V_EstimatedWeight"
							    }
						    ]
						},
						{
						    "CONCEPTUAL_NAME": "manufacturedItemClassification",
						    "DB_MAPPING": [
						      	{
						        	"DB": "_3DSpaceDB",
						        	"Mapping": "DELFmiFunctionPPRCreateReference.V_ManufacturedItemClassification"
						      	}
						    ]
						},
						{
						    "CONCEPTUAL_NAME": "materialCategory",
						    "DB_MAPPING": [
						      	{
						        	"DB": "_3DSpaceDB",
						        	"Mapping": "DELFmiFunctionPPRCreateReference.V_MaterialCategory"
						      	}
						    ]
						},
						{
						    "CONCEPTUAL_NAME": "spareManufacturedItem",
						    "DB_MAPPING": [
						      	{
						        	"DB": "_3DSpaceDB",
						        	"Mapping": "DELFmiFunctionPPRCreateReference.V_SpareManufacturedItem"
						      	}
						    ]
						},
						{
						    "CONCEPTUAL_NAME": "targetReleaseDate",
						    "DB_MAPPING": [
						      	{
						        	"DB": "_3DSpaceDB",
						        	"Mapping": "DELFmiFunctionPPRCreateReference.V_TargetReleaseDate"
						      	}
						    ]
						}
				  	]
                },
                {
                    "CONCEPTUAL_NAME": "DELFmiFunctionPPRAddReference",
                    "PARENT_TYPE": "dsmfg:MfgItem",
                    "IS_ABSTRACT": "TRUE",
                    "DB_MAPPING": [
                        {
                            "DB": "_3DSpaceDB",
                            "Mapping": "DELFmiFunctionPPRAddReference",
                            "Behavior": "REFERENCE"
                        },
                        {
                            "DB": "_Index",
                            "Mapping": "DELFmiFunctionPPRAddReference",
                            "Behavior": "REFERENCE"
                        }
                    ],
                    "Attributes": [
                    	{
						    "CONCEPTUAL_NAME": "estimatedCost",
						    "DB_MAPPING": [
						      	{
						        	"DB": "_3DSpaceDB",
						        	"Mapping": "DELFmiFunctionPPRAddReference.V_EstimatedCost"
						      	}
						    ]
						},
						{
						    "CONCEPTUAL_NAME": "estimatedCostCurrency",
						    "DB_MAPPING": [
						      	{
						        	"DB": "_3DSpaceDB",
						        	"Mapping": "DELFmiFunctionPPRAddReference.V_EstimatedCostCurrency"
						      	}
						    ]
					    },
					    {
						    "CONCEPTUAL_NAME": "estimatedLeadTimeDescription",
						    "DB_MAPPING": [
						      	{
						        	"DB": "_3DSpaceDB",
						        	"Mapping": "DELFmiFunctionPPRAddReference.V_EstimatedLeadTimeDescription"
						      	}
						    ]
						},
						{
						    "CONCEPTUAL_NAME": "estimatedWeight",
						    "DB_MAPPING": [
							    {
							        "DB": "_3DSpaceDB",
							        "Mapping": "DELFmiFunctionPPRAddReference.V_EstimatedWeight"
							    }
						    ]
						},
						{
						    "CONCEPTUAL_NAME": "manufacturedItemClassification",
						    "DB_MAPPING": [
						      	{
						        	"DB": "_3DSpaceDB",
						        	"Mapping": "DELFmiFunctionPPRAddReference.V_ManufacturedItemClassification"
						      	}
						    ]
						},
						{
						    "CONCEPTUAL_NAME": "materialCategory",
						    "DB_MAPPING": [
						      	{
						        	"DB": "_3DSpaceDB",
						        	"Mapping": "DELFmiFunctionPPRAddReference.V_MaterialCategory"
						      	}
						    ]
						},
						{
						    "CONCEPTUAL_NAME": "spareManufacturedItem",
						    "DB_MAPPING": [
						      	{
						        	"DB": "_3DSpaceDB",
						        	"Mapping": "DELFmiFunctionPPRAddReference.V_SpareManufacturedItem"
						      	}
						    ]
						},
						{
						    "CONCEPTUAL_NAME": "targetReleaseDate",
						    "DB_MAPPING": [
						      	{
						        	"DB": "_3DSpaceDB",
						        	"Mapping": "DELFmiFunctionPPRAddReference.V_TargetReleaseDate"
						      	}
						    ]
						}
                    ]
                },
                {
                    "CONCEPTUAL_NAME": "DELFmiFunctionPPRDiscreteReference",
                    "PARENT_TYPE": "dsmfg:MfgItem",
                    "IS_ABSTRACT": "TRUE",
                    "DB_MAPPING": [
                        {
                            "DB": "_3DSpaceDB",
                            "Mapping": "DELFmiFunctionPPRDiscreteReference",
                            "Behavior": "REFERENCE"
                        },
                        {
                            "DB": "_Index",
                            "Mapping": "DELFmiFunctionPPRDiscreteReference",
                            "Behavior": "REFERENCE"
                        }
                    ],
                    "Attributes": []
                },
                {
                    "CONCEPTUAL_NAME": "DELFmiContinuousFunctionReference",
                    "PARENT_TYPE": "dsmfg:MfgItem",
                    "IS_ABSTRACT": "TRUE",
                    "DB_MAPPING": [
                        {
                            "DB": "_3DSpaceDB",
                            "Mapping": "DELFmiContinuousFunctionReference",
                            "Behavior": "REFERENCE"
                        },
                        {
                            "DB": "_Index",
                            "Mapping": "DELFmiContinuousFunctionReference",
                            "Behavior": "REFERENCE"
                        }
                    ],
                    "Attributes": [
                    	{
						    "CONCEPTUAL_NAME": "estimatedCost",
						    "DB_MAPPING": [
						      	{
						        	"DB": "_3DSpaceDB",
						        	"Mapping": "DELFmiFunctionPPRContinuousReference.V_EstimatedCost"
						      	}
						    ]
						},
						{
						    "CONCEPTUAL_NAME": "estimatedCostCurrency",
						    "DB_MAPPING": [
						      	{
						        	"DB": "_3DSpaceDB",
						        	"Mapping": "DELFmiFunctionPPRContinuousReference.V_EstimatedCostCurrency"
						      	}
						    ]
					    },
					    {
						    "CONCEPTUAL_NAME": "estimatedLeadTimeDescription",
						    "DB_MAPPING": [
						      	{
						        	"DB": "_3DSpaceDB",
						        	"Mapping": "DELFmiFunctionPPRContinuousReference.V_EstimatedLeadTimeDescription"
						      	}
						    ]
						},
						{
						    "CONCEPTUAL_NAME": "estimatedWeight",
						    "DB_MAPPING": [
							    {
							        "DB": "_3DSpaceDB",
							        "Mapping": "DELFmiFunctionPPRContinuousReference.V_EstimatedWeight"
							    }
						    ]
						},
						{
						    "CONCEPTUAL_NAME": "manufacturedItemClassification",
						    "DB_MAPPING": [
						      	{
						        	"DB": "_3DSpaceDB",
						        	"Mapping": "DELFmiFunctionPPRContinuousReference.V_ManufacturedItemClassification"
						      	}
						    ]
						},
						{
						    "CONCEPTUAL_NAME": "materialCategory",
						    "DB_MAPPING": [
						      	{
						        	"DB": "_3DSpaceDB",
						        	"Mapping": "DELFmiFunctionPPRContinuousReference.V_MaterialCategory"
						      	}
						    ]
						},
						{
						    "CONCEPTUAL_NAME": "spareManufacturedItem",
						    "DB_MAPPING": [
						      	{
						        	"DB": "_3DSpaceDB",
						        	"Mapping": "DELFmiFunctionPPRContinuousReference.V_SpareManufacturedItem"
						      	}
						    ]
						},
						{
						    "CONCEPTUAL_NAME": "targetReleaseDate",
						    "DB_MAPPING": [
						      	{
						        	"DB": "_3DSpaceDB",
						        	"Mapping": "DELFmiFunctionPPRContinuousReference.V_TargetReleaseDate"
						      	}
						    ]
						}
                    ]
                },
                {
                    "CONCEPTUAL_NAME": "CA",
                    "PARENT_TYPE": "DELFmiFunctionPPRCreateReference",
                    "DB_MAPPING": [
                        {
                            "DB": "_3DSpaceDB",
                            "Mapping": "CreateAssembly",
                            "Behavior": "REFERENCE"
                        },
                        {
                            "DB": "_Index",
                            "Mapping": "CreateAssembly",
                            "Behavior": "REFERENCE"
                        }
                    ],
                    "Attributes": [
                        {
                            "CONCEPTUAL_NAME": "outsourced",
                            "DB_MAPPING": [
                                {
                                    "DB": "_3DSpaceDB",
                                    "Mapping": "V_Outsourced"
                                }
                            ],
                            "Transforms" : 
							[
								{
									"DB" : "_3DSpaceDB",
									"Class" : "com.dassault_systemes.delmia.crud.mbomservices.attributes.transforms.AttributeCreateAssemblyOutsourcedTransform"
								}
							]
                        },
                        {
                            "CONCEPTUAL_NAME": "planningRequired",
                            "DB_MAPPING": [
                                {
                                    "DB": "_3DSpaceDB",
                                    "Mapping": "V_NeedDedicatedSystem"
                                }
                            ],
                            "Transforms" : 
							[
								{
									"DB" : "_3DSpaceDB",
									"Class" : "com.dassault_systemes.delmia.crud.mbomservices.attributes.transforms.AttributeMfgItemPlanningRequiredTransform"
								}
							]
                        }
                    ]
                },
                {
                    "CONCEPTUAL_NAME": "Drill",
                    "PARENT_TYPE": "DELFmiFunctionPPRDiscreteReference",
                    "DB_MAPPING": [
                        {
                            "DB": "_3DSpaceDB",
                            "Mapping": "Drill",
                            "Behavior": "REFERENCE"
                        },
                        {
                            "DB": "_Index",
                            "Mapping": "Drill",
                            "Behavior": "REFERENCE"
                        }
                    ],
                    "Attributes": [
                        {
                            "CONCEPTUAL_NAME": "depthOfFeature",
                            "DB_MAPPING": [
                                {
                                    "DB": "_3DSpaceDB",
                                    "Mapping": "Drill.V_DepthOfFeature"
                                }
                            ]
                        },
                        {
                            "CONCEPTUAL_NAME": "diameterOfFeature",
                            "DB_MAPPING": [
                                {
                                    "DB": "_3DSpaceDB",
                                    "Mapping": "Drill.V_DiameterOfFeature"
                                }
                            ]
                        }
                    ]
                },
                {
                    "CONCEPTUAL_NAME": "Pre Drill",
                    "PARENT_TYPE": "DELFmiFunctionPPRDiscreteReference",
                    "DB_MAPPING": [
                        {
                            "DB": "_3DSpaceDB",
                            "Mapping": "PreDrill",
                            "Behavior": "REFERENCE"
                        },
                        {
                            "DB": "_Index",
                            "Mapping": "PreDrill",
                            "Behavior": "REFERENCE"
                        }
                    ],
                    "Attributes": [
                        {
                            "CONCEPTUAL_NAME": "depthOfFeature",
                            "DB_MAPPING": [
                                {
                                    "DB": "_3DSpaceDB",
                                    "Mapping": "PreDrill.V_DepthOfFeature"
                                }
                            ]
                        },
                        {
                            "CONCEPTUAL_NAME": "diameterOfFeature",
                            "DB_MAPPING": [
                                {
                                    "DB": "_3DSpaceDB",
                                    "Mapping": "PreDrill.V_DiameterOfFeature"
                                }
                            ]
                        }
                    ]
                },
                {
                    "CONCEPTUAL_NAME": "Manufacturing Kit",
                    "PARENT_TYPE": "DELFmiFunctionPPRCreateReference",
                    "DB_MAPPING": [
                        {
                            "DB": "_3DSpaceDB",
                            "Mapping": "CreateKit",
                            "Behavior": "REFERENCE"
                        },
                        {
                            "DB": "_Index",
                            "Mapping": "CreateKit",
                            "Behavior": "REFERENCE"
                        }
                    ],
                    "Attributes": [
                        {
                            "CONCEPTUAL_NAME": "outsourced",
                            "DB_MAPPING": [
                                {
                                    "DB": "_3DSpaceDB",
                                    "Mapping": "V_Outsourced"
                                }
                            ],
                            "Transforms" : 
							[
								{
									"DB" : "_3DSpaceDB",
									"Class" : "com.dassault_systemes.delmia.crud.mbomservices.attributes.transforms.AttributeMfgItemOutsourcedTransform"
								}
							]
                        },
                        {
                            "CONCEPTUAL_NAME": "planningRequired",
                            "DB_MAPPING": [
                                {
                                    "DB": "_3DSpaceDB",
                                    "Mapping": "V_NeedDedicatedSystem"
                                }
                            ],
                            "Transforms" : 
							[
								{
									"DB" : "_3DSpaceDB",
									"Class" : "com.dassault_systemes.delmia.crud.mbomservices.attributes.transforms.AttributeMfgItemPlanningRequiredTransform"
								}
							]
                        }
                    ]
                },
                {
                    "CONCEPTUAL_NAME": "Manufacturing Material",
                    "PARENT_TYPE": "DELFmiFunctionPPRCreateReference",
                    "DB_MAPPING": [
                        {
                            "DB": "_3DSpaceDB",
                            "Mapping": "CreateMaterial",
                            "Behavior": "REFERENCE"
                        },
                        {
                            "DB": "_Index",
                            "Mapping": "CreateMaterial",
                            "Behavior": "REFERENCE"
                        }
                    ],
                    "Attributes": [
                        {
                            "CONCEPTUAL_NAME": "outsourced",
                            "DB_MAPPING": [
                                {
                                    "DB": "_3DSpaceDB",
                                    "Mapping": "V_Outsourced"
                                }
                            ],
                            "Transforms" : 
							[
								{
									"DB" : "_3DSpaceDB",
									"Class" : "com.dassault_systemes.delmia.crud.mbomservices.attributes.transforms.AttributeMfgItemOutsourcedTransform"
								}
							]
                        },
                        {
                            "CONCEPTUAL_NAME": "planningRequired",
                            "DB_MAPPING": [
                                {
                                    "DB": "_3DSpaceDB",
                                    "Mapping": "V_NeedDedicatedSystem"
                                }
                            ],
                            "Transforms" : 
							[
								{
									"DB" : "_3DSpaceDB",
									"Class" : "com.dassault_systemes.delmia.crud.mbomservices.attributes.transforms.AttributeMfgItemPlanningRequiredTransform"
								}
							]
                        }
                    ]
                },
                {
                    "CONCEPTUAL_NAME": "Manufactured Part",
                    "PARENT_TYPE": "DELFmiFunctionPPRCreateReference",
                    "DB_MAPPING": [
                        {
                            "DB": "_3DSpaceDB",
                            "Mapping": "ElementaryEndItem",
                            "Behavior": "REFERENCE"
                        },
                        {
                            "DB": "_Index",
                            "Mapping": "ElementaryEndItem",
                            "Behavior": "REFERENCE"
                        }
                    ],
                    "Attributes": [
                        {
                            "CONCEPTUAL_NAME": "outsourced",
                            "DB_MAPPING": [
                                {
                                    "DB": "_3DSpaceDB",
                                    "Mapping": "V_Outsourced"
                                }
                            ],
                            "Transforms" : 
							[
								{
									"DB" : "_3DSpaceDB",
									"Class" : "com.dassault_systemes.delmia.crud.mbomservices.attributes.transforms.AttributeMfgItemOutsourcedTransform"
								}
							]
                        },
                        {
                            "CONCEPTUAL_NAME": "planningRequired",
                            "DB_MAPPING": [
                                {
                                    "DB": "_3DSpaceDB",
                                    "Mapping": "V_NeedDedicatedSystem"
                                }
                            ],
                            "Transforms" : 
							[
								{
									"DB" : "_3DSpaceDB",
									"Class" : "com.dassault_systemes.delmia.crud.mbomservices.attributes.transforms.AttributeMfgItemPlanningRequiredTransform"
								}
							]
                        }
                    ]
                },
                {
                    "CONCEPTUAL_NAME": "Manufacturing Installation",
                    "PARENT_TYPE": "DELFmiFunctionPPRCreateReference",
                    "DB_MAPPING": [
                        {
                            "DB": "_3DSpaceDB",
                            "Mapping": "Installation",
                            "Behavior": "REFERENCE"
                        },
                        {
                            "DB": "_Index",
                            "Mapping": "Installation",
                            "Behavior": "REFERENCE"
                        }
                    ],
                    "Attributes": [
                        {
                            "CONCEPTUAL_NAME": "planningRequired",
                            "DB_MAPPING": [
                                {
                                    "DB": "_3DSpaceDB",
                                    "Mapping": "V_NeedDedicatedSystem"
                                }
                            ],
                            "Transforms" : 
							[
								{
									"DB" : "_3DSpaceDB",
									"Class" : "com.dassault_systemes.delmia.crud.mbomservices.attributes.transforms.AttributeMfgItemPlanningRequiredTransform"
								}
							]
                        }
                    ]
                },
                {
                    "CONCEPTUAL_NAME": "Provide",
                    "PARENT_TYPE": "DELFmiFunctionPPRCreateReference",
                    "DB_MAPPING": [
                        {
                            "DB": "_3DSpaceDB",
                            "Mapping": "Provide",
                            "Behavior": "REFERENCE"
                        },
                        {
                            "DB": "_Index",
                            "Mapping": "Provide",
                            "Behavior": "REFERENCE"
                        }
                    ]
                },
                {
                    "CONCEPTUAL_NAME": "Continuous Manufactured Material",
                    "PARENT_TYPE": "DELFmiContinuousFunctionReference",
                    "DB_MAPPING": [
                        {
                            "DB": "_3DSpaceDB",
                            "Mapping": "ProcessContinuousCreateMaterial",
                            "Behavior": "REFERENCE"
                        },
                        {
                            "DB": "_Index",
                            "Mapping": "ProcessContinuousCreateMaterial",
                            "Behavior": "REFERENCE"
                        }
                    ],
                    "Attributes": [
                        {
                            "CONCEPTUAL_NAME": "outsourced",
                            "DB_MAPPING": [
                                {
                                    "DB": "_3DSpaceDB",
                                    "Mapping": "V_Outsourced"
                                }
                            ],
                            "Transforms" : 
							[
								{
									"DB" : "_3DSpaceDB",
									"Class" : "com.dassault_systemes.delmia.crud.mbomservices.attributes.transforms.AttributeMfgItemOutsourcedTransform"
								}
							]
                        },
                        {
                            "CONCEPTUAL_NAME": "planningRequired",
                            "DB_MAPPING": [
                                {
                                    "DB": "_3DSpaceDB",
                                    "Mapping": "V_NeedDedicatedSystem"
                                }
                            ],
                            "Transforms" : 
							[
								{
									"DB" : "_3DSpaceDB",
									"Class" : "com.dassault_systemes.delmia.crud.mbomservices.attributes.transforms.AttributeMfgItemPlanningRequiredTransform"
								}
							]
                        },
                        {
                            "CONCEPTUAL_NAME": "magnitude",
                            "Checkers": [
                                {
                                    "DB": "_3DSpaceDB",
                                    "Class": "com.dassault_systemes.delmia.crud.mbomservices.attributes.checkers.PPRContinuousReferenceAttributeMagnitudeChecker"
                                }
                            ],
                            "Transforms": [
                                {
                                    "DB": "_3DSpaceDB",
                                    "Class": "com.dassault_systemes.delmia.crud.mbomservices.attributes.transforms.AttributePPRContinuousReferenceMagnitudeTransform"
                                }
                            ]
                        }
                    ]
                },
                {
                    "CONCEPTUAL_NAME": "Continuous Provided Material",
                    "PARENT_TYPE": "DELFmiContinuousFunctionReference",
                    "DB_MAPPING": [
                        {
                            "DB": "_3DSpaceDB",
                            "Mapping": "ProcessContinuousProvide",
                            "Behavior": "REFERENCE"
                        },
                        {
                            "DB": "_Index",
                            "Mapping": "ProcessContinuousProvide",
                            "Behavior": "REFERENCE"
                        }
                    ],
                    "Attributes": [
                        {
                            "CONCEPTUAL_NAME": "magnitude",
                            "Checkers": [
                                {
                                    "DB": "_3DSpaceDB",
                                    "Class": "com.dassault_systemes.delmia.crud.mbomservices.attributes.checkers.PPRContinuousReferenceAttributeMagnitudeChecker"
                                }
                            ],
                            "Transforms": [
                                {
                                    "DB": "_3DSpaceDB",
                                    "Class": "com.dassault_systemes.delmia.crud.mbomservices.attributes.transforms.AttributePPRContinuousReferenceMagnitudeTransform"
                                }
                            ]
                        }
                    ]
                },
                {
                    "CONCEPTUAL_NAME": "dsmfg:MfgItemInstance",
                    "PARENT_TYPE": "PLMInstance",
                    "DB_MAPPING": [
                        {
                            "DB": "_3DSpaceDB",
                            "Mapping": "DELFmiFunctionInstance",
                            "Behavior": "INSTANCE"
                        },
                        {
                            "DB": "_Index",
                            "Mapping": "DELFmiFunctionInstance",
                            "Behavior": "INSTANCE"
                        }
                    ],
                    "Dependencies": [
                        {
                            "CONCEPTUAL_NAME": "CA",
                            "Dependencies_Attributes": [
                                "From_IDs",
                                "TO_IDs"
                            ]
                        },
                        {
                            "CONCEPTUAL_NAME": "Provide",
                            "Dependencies_Attributes": [
                                "TO_IDs"
                            ]
                        }
                    ],
                    "Attributes": [
                        {
                            "CONCEPTUAL_NAME": "name",
                            "DB_MAPPING": [
                                {
                                    "DB": "_3DSpaceDB",
                                    "Mapping": "PLM_ExternalID"
                                }
                            ]
                        },
                        {
                            "CONCEPTUAL_NAME": "title",
                            "DB_MAPPING": [
                                {
                                    "DB": "_3DSpaceDB",
                                    "Mapping": "V_Name"
                                }
                            ]
                        },
                        {
                            "CONCEPTUAL_NAME": "description",
                            "DB_MAPPING": [
                                {
                                    "DB": "_3DSpaceDB",
                                    "Mapping": "V_description"
                                }
                            ]
                        },
                        {
                            "CONCEPTUAL_NAME": "From_IDs",
                            "State": "MANDATORY",
                            "Checkers": [
                                {
                                    "DB": "_3DSpaceDB",
                                    "Class": "com.dassault_systemes.delmia.crud.services.attributes.checkers.AttributeNotNullAndUniqueValueChecker"
                                }
                            ]
                        },
                        {
                            "CONCEPTUAL_NAME": "TO_IDs",
                            "State": "MANDATORY",
                            "Checkers": [
                                {
                                    "DB": "_3DSpaceDB",
                                    "Class": "com.dassault_systemes.delmia.crud.services.attributes.checkers.AttributeNotNullAndUniqueValueChecker"
                                }
                            ]
                        },
                        {
                            "CONCEPTUAL_NAME": "quantity",
                            "Checkers": [
                                {
                                    "DB": "_3DSpaceDB",
                                    "Class": "com.dassault_systemes.delmia.crud.mbomservices.attributes.checkers.DELFmiContQuantityExtnAttributeQuantityChecker"
                                }
                            ],
                            "Setters": [
                                {
                                    "DB": "_3DSpaceDB",
                                    "Class": "com.dassault_systemes.delmia.crud.mbomservices.attributes.setters.DELFmiContQuantityExtnAttributeQuantitySetter"
                                }
                            ]
                        }
                    ]
                },
                {
                    "CONCEPTUAL_NAME": "DELFmiFunctionIdentifiedInstance",
                    "PARENT_TYPE": "dsmfg:MfgItemInstance",
                    "DB_MAPPING": [
                        {
                            "DB": "_3DSpaceDB",
                            "Mapping": "DELFmiFunctionIdentifiedInstance",
                            "Behavior": "INSTANCE"
                        },
                        {
                            "DB": "_Index",
                            "Mapping": "DELFmiFunctionIdentifiedInstance",
                            "Behavior": "INSTANCE"
                        }
                    ]
                },
                {
                    "CONCEPTUAL_NAME": "ProcessInstanceContinuous",
                    "PARENT_TYPE": "dsmfg:MfgItemInstance",
                    "DB_MAPPING": [
                        {
                            "DB": "_3DSpaceDB",
                            "Mapping": "ProcessInstanceContinuous",
                            "Behavior": "INSTANCE"
                        },
                        {
                            "DB": "_Index",
                            "Mapping": "ProcessInstanceContinuous",
                            "Behavior": "INSTANCE"
                        }
                    ]
                },
                {
					"CONCEPTUAL_NAME" : "DELFmiProcessImplementCnx",
					"DB_MAPPING" : 
					[
						{
							"DB" : "_3DSpaceDB",
							"Mapping" : "DELFmiProcessImplementCnx",
							"Behavior" : "CUSTOM",
                            "Class" : "com.dassault_systemes.delmia.crud.bytype.impl.DELMIACRUDByConceptualTypeMfgItemScopeLink"
						}
					],
                    "Dependencies" : 
					[
						{
							"CONCEPTUAL_NAME" : "CA",
							"Dependencies_Attributes" : 
							[
								"From_IDs"
							]
						},
						{
							"CONCEPTUAL_NAME" : "VPMReference",
							"Dependencies_Attributes" : 
							[
								"TO_IDs"
							]
						}
					],
					"Attributes" : 
					[
						{
							"CONCEPTUAL_NAME" : "From_IDs",
                            "State" : "MANDATORY",
                            "Checkers" : 
							[
								{
									"DB" : "_3DSpaceDB",
									"Class" : "com.dassault_systemes.delmia.crud.services.attributes.checkers.AttributeNotNullAndUniqueValueChecker"
								}
							]
						},
                        {
							"CONCEPTUAL_NAME" : "TO_IDs",
                            "State" : "MANDATORY",
                            "Checkers" : 
							[
								{
									"DB" : "_3DSpaceDB",
									"Class" : "com.dassault_systemes.delmia.crud.services.attributes.checkers.AttributeNotNullAndUniqueValueChecker"
								}
							],
							"Getters" : 
							[
								{
									"DB" : "_3DSpaceDB",
									"Class" : "com.dassault_systemes.delmia.crud.mbomservices.attributes.getters.ScopeEngItemFromMfgItemCustomGetter"
								}
							]							
						},
						{
							"CONCEPTUAL_NAME" : "scopeEngItemId",
							"Getters" : 
							[
								{
									"DB" : "_3DSpaceDB",
									"Class" : "com.dassault_systemes.delmia.crud.mbomservices.attributes.getters.ScopeEngItemFromMfgItemCustomGetter"
								}
							]
						}
					]
				},
				{
					"CONCEPTUAL_NAME" : "dsmfg:ResultingEngItem",
					"DB_MAPPING" : 
					[
						{
							"DB" : "_3DSpaceDB",
							"Mapping" : "DELFmiProcessPrereqMaterializationCnx",
							"Behavior" : "CUSTOM",
                            "Class" : "com.dassault_systemes.delmia.crud.bytype.impl.DELMIACRUDByConceptualTypeMfgItemResultingEngItemLink"
						}
					],
                    "Dependencies" : 
					[
						{
							"CONCEPTUAL_NAME" : "CA",
							"Dependencies_Attributes" : 
							[
								"From_IDs"
							]
						},
						{
							"CONCEPTUAL_NAME" : "VPMReference",
							"Dependencies_Attributes" : 
							[
								"TO_IDs"
							]
						}
					],
					"Attributes" : 
					[
						{
							"CONCEPTUAL_NAME" : "From_IDs",
                            "State" : "MANDATORY",
                            "Checkers" : 
							[
								{
									"DB" : "_3DSpaceDB",
									"Class" : "com.dassault_systemes.delmia.crud.services.attributes.checkers.AttributeNotNullAndUniqueValueChecker"
								}
							]
						},
                        {
							"CONCEPTUAL_NAME" : "TO_IDs",
                            "State" : "MANDATORY",
                            "Checkers" : 
							[
								{
									"DB" : "_3DSpaceDB",
									"Class" : "com.dassault_systemes.delmia.crud.services.attributes.checkers.AttributeNotNullAndUniqueValueChecker"
								}
							]
						},
						{
							"CONCEPTUAL_NAME" : "resultingEngItemId",
							"Getters" : 
							[
								{
									"DB" : "_3DSpaceDB",
									"Class" : "com.dassault_systemes.delmia.crud.mbomservices.attributes.getters.ResultingEngItemFromDataMaterializationCnxCustomGetter"
								}
							]
						},
			            {
			              "CONCEPTUAL_NAME": "usage",
			              "DB_MAPPING": [
			                {
			                  "DB": "_3DSpaceDB",
			                  "Mapping": "PLMEntity.V_usage"
			                }
			              ],
			              "Checkers": [
			                {
			                  "DB": "_3DSpaceDB",
			                  "Class": "com.dassault_systemes.delmia.crud.services.attributes.checkers.AttributeDefaultChecker"
			                }
			              ],
			              "Setters": [
			                {
			                  "DB": "_3DSpaceDB",
			                  "Class": "com.dassault_systemes.delmia.crud.mbomservices.attributes.setters.AttributeResultingEngItemUsageSetter"
			                }
			              ]
			            }						
					]
				},
				{
					"CONCEPTUAL_NAME" : "PLMAssignmentFilterCnx",
					"DB_MAPPING" : 
					[
						{
							"DB" : "_3DSpaceDB",
							"Mapping" : "PLMAssignmentFilterCnx",
							"Behavior" : "CUSTOM",
                            "Class" : "com.dassault_systemes.delmia.crud.bytype.impl.DELMIACRUDByConceptualTypeMfgItemAssignmentFilterLink"
						}
					],
                    "Dependencies" : 
					[
						{
							"CONCEPTUAL_NAME" : "CA",
							"Dependencies_Attributes" : 
							[
								"From_IDs"
							]
						},
						{
							"CONCEPTUAL_NAME" : "VPMReference",
							"Dependencies_Attributes" : 
							[
								"TO_IDs"
							]
						}
					],
					"Attributes" : 
					[
						{
							"CONCEPTUAL_NAME" : "From_IDs",
                            "State" : "MANDATORY",
                            "Checkers" : 
							[
								{
									"DB" : "_3DSpaceDB",
									"Class" : "com.dassault_systemes.delmia.crud.services.attributes.checkers.AttributeNotNullAndUniqueValueChecker"
								}
							],
							"Getters" : 
							[
								{
									"DB" : "_3DSpaceDB",
									"Class" : "com.dassault_systemes.delmia.crud.mbomservices.attributes.getters.MfgItemFromAssignmentFilterEngOccurrence"
								}
							]							
						},
                        {
							"CONCEPTUAL_NAME" : "TO_IDs",
                            "State" : "MANDATORY",
                            "Checkers" : 
							[
								{
									"DB" : "_3DSpaceDB",
									"Class" : "com.dassault_systemes.delmia.crud.services.attributes.checkers.AttributeNotNullAndUniqueValueCheckerEx"
								}
							],
							"Getters" : 
							[
								{
									"DB" : "_3DSpaceDB",
									"Class" : "com.dassault_systemes.delmia.crud.mbomservices.attributes.getters.AssignmentFilterCnxFromMfgItemCustomGetter"
								}
							]							
						}
					]
				},
				{
					"CONCEPTUAL_NAME" : "PartialScopeEngItem",
					"DB_MAPPING" : 
					[
						{
							"DB" : "_3DSpaceDB",
							"Mapping" : "PartialScopeEngItem",
							"Behavior" : "CUSTOM",
                            "Class" : "com.dassault_systemes.delmia.crud.bytype.impl.DELMIACRUDByConceptualTypeMfgItemPartialScopeLink"
						}
					],
                    "Dependencies" : 
					[
						{
							"CONCEPTUAL_NAME" : "dsmfg:MfgItem",
							"Dependencies_Attributes" : 
							[
								"From_IDs"
							]
						},
						{
							"CONCEPTUAL_NAME" : "VPMReference",
							"Dependencies_Attributes" : 
							[
								"TO_IDs"
							]
						}
					],
					"Attributes" : 
					[
						{
							"CONCEPTUAL_NAME" : "From_IDs",
                            "State" : "MANDATORY",
                            "Checkers" : 
							[
								{
									"DB" : "_3DSpaceDB",
									"Class" : "com.dassault_systemes.delmia.crud.services.attributes.checkers.AttributeNotNullAndUniqueValueChecker"
								}
							]
						},
                        {
							"CONCEPTUAL_NAME" : "TO_IDs",
                            "State" : "MANDATORY",
                            "Checkers" : 
							[
								{
									"DB" : "_3DSpaceDB",
									"Class" : "com.dassault_systemes.delmia.crud.services.attributes.checkers.AttributeNotNullAndUniqueValueChecker"
								}
							],
							"Getters" : 
							[
								{
									"DB" : "_3DSpaceDB",
									"Class" : "com.dassault_systemes.delmia.crud.mbomservices.attributes.getters.PartialScopeEngItemFromMfgItemCustomGetter"
								}
							]							
						}				
					]
				},
				{
					"CONCEPTUAL_NAME" : "ImplementedEngOccurrence",
					"DB_MAPPING" : 
					[
						{
							"DB" : "_3DSpaceDB",
							"Mapping" : "ImplementedEngOccurrence",
							"Behavior" : "CUSTOM",
                            "Class" : "com.dassault_systemes.delmia.crud.bytype.impl.DELMIACRUDByConceptualTypeImplementedEngOccurrence"
						}
					],
                    "Dependencies" : 
					[
						{
							"CONCEPTUAL_NAME" : "CA",
							"Dependencies_Attributes" : 
							[
								"From_IDs"
							]
						},
						{
							"CONCEPTUAL_NAME" : "VPMReference",
							"Dependencies_Attributes" : 
							[
								"TO_IDs"
							]
						}
					],
					"Attributes" : 
					[
						{
							"CONCEPTUAL_NAME" : "From_IDs",
                            "State" : "MANDATORY",
                            "Checkers" : 
							[
								{
									"DB" : "_3DSpaceDB",
									"Class" : "com.dassault_systemes.delmia.crud.services.attributes.checkers.AttributeNotNullAndUniqueValueChecker"
								}
							]
						},
                        {
							"CONCEPTUAL_NAME" : "TO_IDs",
                            "State" : "MANDATORY",
                            "Checkers" : 
							[
								{
									"DB" : "_3DSpaceDB",
									"Class" : "com.dassault_systemes.delmia.crud.services.attributes.checkers.AttributeNotNullAndUniqueValueChecker"
								}
							],
							"Getters" : 
							[
								{
									"DB" : "_3DSpaceDB",
									"Class" : "com.dassault_systemes.delmia.crud.mbomservices.attributes.getters.ImplementedEngOccurrenceFromMfgItemInstanceCustomGetter"
								}
							]							
						}
					]
				}				
            ]
        }
    ]
}
